pyfractal/__init__.py
pyfractal/curve.py
pyfractal/fastfractal.py
pyfractal/gui.py
pyfractal/parameters.py
pyfractal/quickfractaltrial.py
pyfractal/rules_input.py
pyfractal/turtle.py
pyfractal/curves/19_Curve2_FractalFlower.json
pyfractal/curves/2_HargerHeighwayDragon.json
pyfractal/curves/2_PolyaSweep.json
pyfractal/curves/3_Curve1.json
pyfractal/curves/3_Curve2.json
pyfractal/curves/3_Curve3.json
pyfractal/curves/3_Curve4.json
pyfractal/curves/3_Curve5.json
pyfractal/curves/3_Curve5_Horse.json
pyfractal/curves/3_Curve6.json
pyfractal/curves/3_Curve7.json
pyfractal/curves/3_InvertedTerDragon.json
pyfractal/curves/3_TerDragon.json
pyfractal/curves/3_YinDragon.json
pyfractal/curves/4_CesaroSweep.json
pyfractal/curves/4_Curve1.json
pyfractal/curves/4_Curve10.json
pyfractal/curves/4_Curve11.json
pyfractal/curves/4_Curve12.json
pyfractal/curves/4_Curve13.json
pyfractal/curves/4_Curve2.json
pyfractal/curves/4_Curve3.json
pyfractal/curves/4_Curve4.json
pyfractal/curves/4_Curve5.json
pyfractal/curves/4_Curve6.json
pyfractal/curves/4_Curve7.json
pyfractal/curves/4_Curve8.json
pyfractal/curves/4_Curve9.json
pyfractal/curves/4_DragonOfEve.json
pyfractal/curves/4_PeanoSweep.json
pyfractal/curves/4_S4-50-64-10-3.json
pyfractal/curves/4_SerpinskiArrowheadCurve.json
pyfractal/curves/4_SerpinskiFamily.json
pyfractal/curves/4_V1Dragon.json
pyfractal/curves/4_V2Dragon.json
pyfractal/curves/5_Curve1Genie.json
pyfractal/curves/5_Curve2_InverseGenie.json
pyfractal/curves/5_Curve3_FuriousDragon.json
pyfractal/curves/5_Curve4_InverseFuriousDragon.json
pyfractal/curves/5_Curve5_InverseHorse.json
pyfractal/curves/5_Curve6_Puppy.json
pyfractal/curves/5_Curve7_Reindeer.json
pyfractal/curves/5_Curve8_FlyingDog.json
pyfractal/curves/5_Curve9.json
pyfractal/curves/5_Dragon.json
pyfractal/curves/5_InnerFlipQuartet.json
pyfractal/curves/5_Pinched5Dragon.json
pyfractal/curves/5_Quartet.json
pyfractal_deut_erium-0.0.4.dist-info/LICENSE
pyfractal_deut_erium-0.0.4.dist-info/METADATA
pyfractal_deut_erium-0.0.4.dist-info/WHEEL
pyfractal_deut_erium-0.0.4.dist-info/top_level.txt
pyfractal_deut_erium-0.0.4.dist-info/RECORD
